[
    {
        "id": 1,
        "nome": "Jack Daniel's",
        "categoria": "Whisky",
        "preco": 29.90,
        "volume": "700 ml",
        "imagem": "assets/pinga.jpg",
        "disponivel": true,
        "promocao": false
    },

    {
        "id": 2,
        "nome": "Absolut",
        "categoria": "Vodka",
        "preco": 22.90,
        "volume": "700 ml",
        "imagem": "assets/pinga.jpg",
        "disponivel": true,
        "promocao": false
    },

    {
        "id": 3,
        "nome": "Red Bull",
        "categoria": "Energéticos",
        "preco": 2.50,
        "volume": "250 ml",
        "imagem": "assets/pinga.jpg",
        "disponivel": true,
        "promocao": true
    }
]